opensarlab_lib/__init__.py
opensarlab_lib/_version.py
opensarlab_lib/aoi_selectors.py
opensarlab_lib/config.py
opensarlab_lib/custom_exceptions.py
opensarlab_lib/gdal_wrap.py
opensarlab_lib/hyp3_wrap.py
opensarlab_lib/plot.py
opensarlab_lib/product_name_parse.py
opensarlab_lib/util.py
opensarlab_lib/widgets.py
opensarlab_lib-0.0.14.dist-info/licenses/LICENSE
opensarlab_lib-0.0.14.dist-info/METADATA
opensarlab_lib-0.0.14.dist-info/WHEEL
opensarlab_lib-0.0.14.dist-info/top_level.txt
opensarlab_lib-0.0.14.dist-info/RECORD
