Metadata-Version: 2.4
Name: opensarlab_lib
Version: 0.0.14
Summary: A Python library to support ASF OpenSARlab's Jupyter Notebook repository https://github.com/ASFOpenSARlab/opensarlab-notebooks
Author-email: ASF OpenSARlab Team <uaf-jupyterhub-asf@alaska.edu>
License-Expression: BSD-3-Clause
Classifier: Programming Language :: Python
Classifier: Programming Language :: Python :: 3
Classifier: Programming Language :: Python :: 3.9
Classifier: Programming Language :: Python :: 3.10
Classifier: Programming Language :: Python :: 3.11
Requires-Python: >=3.9
License-File: LICENSE
Requires-Dist: asf_search
Requires-Dist: cartopy
Requires-Dist: contextily
Requires-Dist: gdal
Requires-Dist: hyp3_sdk
Requires-Dist: ipywidgets
Requires-Dist: IPython
Requires-Dist: matplotlib
Requires-Dist: numpy
Requires-Dist: pandas
Requires-Dist: pyproj
Requires-Dist: requests
Requires-Dist: shapely
Requires-Dist: pyshp
Provides-Extra: dev
Requires-Dist: pytest; extra == "dev"
Requires-Dist: pytest-cov; extra == "dev"
Dynamic: license-file
